tksvg/__init__.py
tksvg/pkgIndex.tcl
tksvg/libtksvg.so
tksvg-0.7.4.dist-info/top_level.txt
tksvg-0.7.4.dist-info/WHEEL
tksvg-0.7.4.dist-info/METADATA
tksvg-0.7.4.dist-info/RECORD
tksvg-0.7.4.dist-info/LICENSE.md
