Metadata-Version: 2.1
Name: tksvg
Version: 0.7.4
Summary: SVG support for PhotoImage in Tk 8.6
Home-page: https://github.com/TkinterEP/tksvg
Author: The tksvg authors
License: GNU GPLv3
Download-URL: https://github.com/TkinterEP/tksvg/releases
Platform: UNKNOWN
License-File: LICENSE.md
Requires-Dist: scikit-build
